kiss/__init__.py
kiss/classes.py
kiss/constants.py
kiss/kiss.py
kiss/util.py
kiss3-8.0.0.dist-info/LICENSE
kiss3-8.0.0.dist-info/METADATA
kiss3-8.0.0.dist-info/WHEEL
kiss3-8.0.0.dist-info/top_level.txt
kiss3-8.0.0.dist-info/RECORD
