Metadata-Version: 2.1
Name: kiss3
Version: 8.0.0
Summary: A pure-Python implementation of serial KISS and KISS-over-TCP protocols for communicating with TNC devices
Author-email: Masen Furer KF7HVM <kf7hvm@0x26.net>, Greg Albrecht W2GMD <oss@undef.net>
License: Copyright 2017 Greg Albrecht and Contributors
Project-URL: Homepage, https://github.com/python-aprs/kiss3
Keywords: Ham Radio,APRS,KISS
Classifier: License :: OSI Approved :: Apache Software License
Classifier: Topic :: Communications :: Ham Radio
Classifier: Programming Language :: Python
Classifier: License :: OSI Approved :: Apache Software License
License-File: LICENSE
